pymaterial-0.1.7.dist-info/METADATA
pymaterial-0.1.7.dist-info/WHEEL
pymaterial-0.1.7.dist-info/licenses/LICENSE
pymaterial/__init__.py
pymaterial/combis/__init__.py
pymaterial/combis/clt/README.md
pymaterial/combis/clt/__init__.py
pymaterial/combis/clt/ply.py
pymaterial/combis/clt/stackup.py
pymaterial/failures/__init__.py
pymaterial/failures/cuntze.py
pymaterial/failures/ifailure.py
pymaterial/failures/maxstress.py
pymaterial/failures/mises.py
pymaterial/failures/puck.py
pymaterial/failures/tsai_hill.py
pymaterial/failures/tsai_wu.py
pymaterial/library/README.md
pymaterial/library/__init__.py
pymaterial/materials/__init__.py
pymaterial/materials/anisotropic.py
pymaterial/materials/isotropic.py
pymaterial/materials/material.py
pymaterial/materials/orthotropic.py
pymaterial/materials/transversely_isotropic.py
pymaterial-0.1.7.dist-info/RECORD
