Metadata-Version: 2.1
Name: pymaterial
Version: 0.1.7
Summary: pyMaterial, library for material and failure modeling.
Author-Email: Willi Zschiebsch <willi.zschiebsch@gmail.com>
License: MIT
Project-URL: Source, https://github.com/Modular-Design/pyMaterial
Project-URL: Issues, https://github.com/Modular-Design/pyMaterial/issues
Requires-Python: >=3.8
Requires-Dist: numpy>=1.24.1
Requires-Dist: pymaterial[test]; extra == "all"
Provides-Extra: all
